notify_widgets/__init__.py
notify_widgets/__main__.py
notify_widgets/data_classes.py
notify_widgets/default_modules.py
notify_widgets/modules.py
notify_widgets/utils.py
notify_widgets-0.1.0.dist-info/METADATA
notify_widgets-0.1.0.dist-info/WHEEL
notify_widgets-0.1.0.dist-info/entry_points.txt
notify_widgets-0.1.0.dist-info/licenses/LICENSE
notify_widgets-0.1.0.dist-info/RECORD
