Metadata-Version: 2.3
Name: notify_widgets
Version: 0.1.0
Summary: Widgets using a notification daemon
Project-URL: Repository, https://codeberg.org/wime/tool-notify-widgets
Author-email: Willem Meijer <willem.meijer@mailbox.org>
License: MIT License
License-File: LICENSE
Keywords: cli,tool,widgets
Classifier: Programming Language :: Python
Requires-Python: >=3.10
